pyampio/__init__.py
pyampio/__main__.py
pyampio/broadcast.py
pyampio/can.py
pyampio/converters.py
pyampio/gateway.py
pyampio/modules.py
pyampio/version.py
pyampio-0.0.2.data/data/pyampio/modules.yaml
pyampio-0.0.2.dist-info/DESCRIPTION.rst
pyampio-0.0.2.dist-info/LICENSE.txt
pyampio-0.0.2.dist-info/METADATA
pyampio-0.0.2.dist-info/RECORD
pyampio-0.0.2.dist-info/WHEEL
pyampio-0.0.2.dist-info/entry_points.txt
pyampio-0.0.2.dist-info/metadata.json
pyampio-0.0.2.dist-info/top_level.txt
