Metadata-Version: 2.0
Name: pyampio
Version: 0.0.2
Summary: A Python Ampio Server USB<->CAN
Home-page: http://github.com/kstaniek/pyampio
Author: Klaudiusz Staniek
Author-email: kstaniek@gmail.com
License: Apache 2.0
Keywords: ampio automation can
Platform: UNKNOWN
Classifier: Development Status :: 3 - Alpha
Classifier: Intended Audience :: Developers
Classifier: Topic :: System :: Hardware :: Hardware Drivers
Classifier: Topic :: Software Development :: Libraries :: Python Modules
Classifier: License :: OSI Approved :: Apache Software License
Classifier: Programming Language :: Python
Classifier: Programming Language :: Python :: 3 :: Only
Classifier: Programming Language :: Python :: 3.4
Classifier: Programming Language :: Python :: 3.5
Classifier: Programming Language :: Python :: 3.6
Requires-Dist: pyserial (==3.4)
Requires-Dist: pyserial-asyncio (==0.4)
Requires-Dist: PyYAML (==3.12)
Requires-Dist: voluptuous (==0.10.5)
Requires-Dist: click (==6.7)
